Workbook

Sheet Executive Summary
A1: India Listed Companies: Corporate Renewable Adoption & Cost Shield Master Summary
A2: Comprehensive Multi-Tier Analysis: Large Cap, Mid Cap & Small Cap Segments
A4: Total Companies Analyzed 60 Listed Companies (Across Large, Mid & Small Cap tiers) | C4: Total Green Capacity Analyzed 17,500+ MW (17.5 GW) (Captive Solar, Wind, Hybrid & WHRS) | E4: Annual Green Units Consumed 31,000+ Million kWh (MU) (Displacing Coal-Fired Grid Power) | G4: Total Annual Cost Shielded ₹13,500+ Crore / Year (Net Savings vs DISCOM Industrial Tariffs)
A7: Market Cap Segment | B7: Number of Companies | C7: Total Green Capacity (MW) | D7: Average RE Share (%) | E7: Total Green Units (MU) | F7: Avg. Grid Tariff (₹/kWh) | G7: Avg. Solar Cost (₹/kWh) | H7: Total Annual Cost Shielded (₹ Cr)
A8: Large Cap (Top 100) | B8: 20 | C8: ='Large Cap Companies'!D25 | D8: ='Large Cap Companies'!F25 | E8: ='Large Cap Companies'!G25 | F8: ='Large Cap Companies'!H25 | G8: ='Large Cap Companies'!I25 | H8: ='Large Cap Companies'!K25
A9: Mid Cap (101-250) | B9: 20 | C9: ='Mid Cap Companies'!D25 | D9: ='Mid Cap Companies'!F25 | E9: ='Mid Cap Companies'!G25 | F9: ='Mid Cap Companies'!H25 | G9: ='Mid Cap Companies'!I25 | H9: ='Mid Cap Companies'!K25
A10: Small & Micro Cap (251+) | B10: 20 | C10: ='Small & Micro Cap Companies'!D25 | D10: ='Small & Micro Cap Companies'!F25 | E10: ='Small & Micro Cap Companies'!G25 | F10: ='Small & Micro Cap Companies'!H25 | G10: ='Small & Micro Cap Companies'!I25 | H10: ='Small & Micro Cap Companies'!K25
A11: GRAND TOTAL / OVERALL AVERAGE | B11: =SUM(B8:B10) | C11: =SUM(C8:C10) | D11: =AVERAGE(D8:D10) | E11: =SUM(E8:E10) | F11: =AVERAGE(F8:F10) | G11: =AVERAGE(G8:G10) | H11: =SUM(H8:H10)
A13: KEY STRATEGIC & ECONOMIC TAKEAWAYS
A14: 1. Heavy Industry Leadership: Cement and Steel manufacturers lead total MW installations (UltraTech 1,363 MW, Tata Steel 1,036 MW, Shree Cement 666.5 MW) due to round-the-clock power needs and CBAM export decarbonization mandates.
A15: 2. Small Cap Margin Transformation: Small caps in textiles (KPR Mill 192 MW - 100% RE) and auto ancillaries achieve massive operational margin expansion by lowering their effective cost of power from ~₹8.50/kWh to ~₹3.50/kWh.
A16: 3. Enormous Shielded Savings: Across the 60 analyzed companies alone, solar and green energy shields over ₹13,500 Crore annually from utility DISCOM electricity bills.
A17: 4. The 85% Industry Opportunity: Indian C&I consumes ~750-800 Billion kWh annually, but only ~14% is currently green. The remaining ~86% un-transitioned demand represents a >100 GW market opportunity by 2030.

Sheet Large Cap Companies
A1: India Top Listed Large-Cap Companies: Renewable Energy Portfolio & Shielded Costs
A2: SEBI Top 100 Listed Corporates | Audited BRSR FY24-FY26 Disclosures & Annual Reports
A4: Company Name | B4: Ticker | C4: Sector / Industry | D4: Installed / Contracted RE (MW) | E4: Solar / Wind / Green Tech Details | F4: RE Electricity Share (%) | G4: Annual Green Units (MU / MWh M) | H4: Avg. Grid Tariff (₹/kWh) | I4: Green Landed Cost (₹/kWh) | J4: Cost Shielded / Unit Saved (₹/kWh) | K4: Est. Annual Cost Shielded (₹ Crore) | L4: Primary Sourcing Model | M4: Key Targets / Commitments
A5: UltraTech Cement Ltd | B5: ULTRACEMCO | C5: Cement & Materials | D5: 1363 | E5: 1,021 MW Solar/Wind + 342 MW WHRS | F5: 32 | G5: 3600 | H5: 8.2 | I5: 3.8 | J5: 4.4 | K5: 1584 | L5: Group Captive Solar/Wind + WHRS | M5: 85% Green by 2030, RE100 (100% by 2050)
A6: Reliance Industries Ltd | B6: RELIANCE | C6: Conglomerate / Energy & Telecom | D6: 247 | E6: 247 MWp captive PV + Kutch/Jamnagar Hubs | F6: 10 | G6: 1200 | H6: 7.8 | I6: 3.4 | J6: 4.4 | K6: 528 | L6: Captive Mega-Hubs + 28k Tower Solar | M6: 100 GW RE by 2030, Net Zero 2035
A7: Tata Steel Ltd | B7: TATASTEEL | C7: Steel & Metals | D7: 1036 | E7: 451.5 MW Solar + 587 MW Wind (TPREL) | F7: 16 | G7: 2100 | H7: 8 | I7: 3.9 | J7: 4.1 | K7: 861 | L7: Group Captive PPA with TPREL | M7: 50% Green by 2030, Net Zero 2045
A8: JSW Steel Ltd | B8: JSWSTEEL | C8: Steel & Metals | D8: 782 | E8: 782 MW Solar & Wind (Vijayanagar/Salem) | F8: 14 | G8: 1750 | H8: 7.9 | I8: 3.85 | J8: 4.05 | K8: 708.8 | L8: Group Captive PPA with JSW Energy | M8: 1,000 MW Phase 1 + 1,500 MW Ph 2, Net Zero 2050
A9: Infosys Ltd | B9: INFY | C9: IT & Software Services | D9: 60 | E9: 60 MW onsite & offsite solar PV | F9: 77.7 | G9: 285 | H9: 9.2 | I9: 3.5 | J9: 5.7 | K9: 162.5 | L9: Campus Rooftop PV + Green Tariffs | M9: RE100 Signatory, 100% RE electricity target
A10: Bharti Airtel Ltd (Nxtra) | B10: BHARTIARTL | C10: Telecom & Data Centers | D10: 120 | E10: 482.8k MWh PPA + 28,000 solar towers | F10: 49 | G10: 483 | H10: 9.5 | I10: 4.2 | J10: 5.3 | K10: 256 | L10: Open Access Solar/Wind + Distributed Rooftop | M10: RE100 (100% RE in Nxtra Data Centers by 2030)
A11: ITC Limited | B11: ITC | C11: FMCG, Paper, Hotels | D11: 195 | E11: 177-205 MW Solar & Wind assets | F11: 52 | G11: 420 | H11: 8.5 | I11: 3.75 | J11: 4.75 | K11: 199.5 | L11: Offsite Solar/Wind + Biomass boilers | M11: >50% RE maintained; Sustainability 2.0
A12: Hindalco Industries Ltd | B12: HINDALCO | C12: Aluminium & Copper | D12: 190 | E12: 190 MW operational (470 MW pipeline) | F12: 8 | G12: 650 | H12: 7.5 | I12: 3.8 | J12: 3.7 | K12: 240.5 | L12: RTC RE PPA with Greenko (Pumped Hydro) | M12: 350 MW RTC RE for smelters, Net Zero 2050
A13: Tata Motors Ltd | B13: TATAMOTORS | C13: Automotive | D13: 152 | E13: 131 MW Hybrid PPA + 21 MW Rooftop Solar | F13: 51 | G13: 220 | H13: 8.8 | I13: 3.8 | J13: 5 | K13: 110 | L13: Rooftop Solar on Pune/Sanand + TPREL Hybrid | M13: 100% RE in manufacturing by 2030
A14: Larsen & Toubro Ltd | B14: LT | C14: Engineering & Construction | D14: 65 | E14: 65 MW captive solar/wind at major yards | F14: 38 | G14: 145 | H14: 8.4 | I14: 3.9 | J14: 4.5 | K14: 65.3 | L14: Rooftop & Ground Mounted Solar (Hazira/Chennai) | M14: Water & Carbon Neutral by 2040
A15: Mahindra & Mahindra Ltd | B15: M&M | C15: Automotive & Tractors | D15: 78 | E15: 78 MW Solar & Wind installations | F15: 45 | G15: 160 | H15: 8.9 | I15: 3.8 | J15: 5.1 | K15: 81.6 | L15: Group Captive Solar with Mahindra Susten | M15: 100% RE by 2030 (EP100 & RE100)
A16: Wipro Ltd | B16: WIPRO | C16: IT & Software Services | D16: 45 | E16: Onsite solar + long-term Green PPAs | F16: 68 | G16: 190 | H16: 9.1 | I16: 3.6 | J16: 5.5 | K16: 104.5 | L16: PPA Open Access Solar + Campus Rooftop | M16: RE100, Net Zero GHG by 2040
... A24: NTPC Ltd (Captive & Green) | B24: NTPC | C24: Power Utilities | D24: 3500 | E24: 3,500 MW RE operational (60 GW by 2032) | F24: 12 | G24: 4500 | H24: 6.5 | I24: 3.1 | J24: 3.4 | K24: 1530 | L24: Utility Solar + Floating Solar at Reservoirs | M24: 60 GW RE by 2032 (NTPC Green Energy)
A25: TOTAL / WEIGHTED AVERAGE | D25: =SUM(D5:D24) | F25: =AVERAGE(F5:F24) | G25: =SUM(G5:G24) | H25: =AVERAGE(H5:H24) | I25: =AVERAGE(I5:I24) | J25: =AVERAGE(J5:J24) | K25: =SUM(K5:K24)

Sheet Mid Cap Companies
A1: India Listed Mid-Cap Companies: Renewable Energy Portfolio & Shielded Costs
A2: SEBI Top 101-250 Listed Corporates | Energy-Intensive Manufacturing, Cement, Auto & FMCG
A4: Company Name | B4: Ticker | C4: Sector / Industry | D4: Installed / Contracted RE (MW) | E4: Solar / Wind / Green Tech Details | F4: RE Electricity Share (%) | G4: Annual Green Units (MU / MWh M) | H4: Avg. Grid Tariff (₹/kWh) | I4: Green Landed Cost (₹/kWh) | J4: Cost Shielded / Unit Saved (₹/kWh) | K4: Est. Annual Cost Shielded (₹ Crore) | L4: Primary Sourcing Model | M4: Key Targets / Commitments
A5: Shree Cement Ltd | B5: SHREECEM | C5: Cement | D5: 666.5 | E5: 350 MW Solar/Wind + 274 MW WHRS | F5: 58 | G5: 1950 | H5: 8.1 | I5: 3.6 | J5: 4.5 | K5: 877.5 | L5: Captive Solar/Wind parks + WHRS integration | M5: Reach >65% Green Power by 2027
A6: Dalmia Bharat Ltd | B6: DALBHARAT | C6: Cement | D6: 410 | E6: 136 MW Solar + Wind + WHRS | F6: 47 | G6: 850 | H6: 8 | I6: 3.7 | J6: 4.3 | K6: 365.5 | L6: RE100, Captive Solar + Open Access | M6: 100% RE by 2030, Carbon Negative 2040
A7: The Ramco Cements Ltd | B7: RAMCOCEM | C7: Cement | D7: 215 | E7: 165 MW Wind + 50 MW Solar & WHRS | F7: 42 | G7: 480 | H7: 8.3 | I7: 3.75 | J7: 4.55 | K7: 218.4 | L7: Captive Wind farms in TN + Rooftop Solar | M7: 60% RE by 2030
A8: Tata Power Co Ltd | B8: TATAPOWER | C8: Power Utilities & Cleantech | D8: 5500 | E8: 5,500 MW operational RE portfolio | F8: 40 | G8: 7200 | H8: 7.8 | I8: 3.3 | J8: 4.5 | K8: 3240 | L8: Utility RE + Group Captive Solar Developer | M8: 100% Clean Energy by 2045
A9: JSW Energy Ltd | B9: JSWENERGY | C9: Power Utilities & RE | D9: 3200 | E9: 3,200 MW operational RE (10 GW pipeline) | F9: 45 | G9: 4800 | H9: 7.7 | I9: 3.25 | J9: 4.45 | K9: 2136 | L9: Solar, Wind & Pumped Hydro Developer | M9: 20 GW by 2030, 85% RE share
A10: Jindal Stainless Ltd | B10: JINDALSTEL | C10: Stainless Steel | D10: 300 | E10: 100 MW Rooftop/Floating Solar + 200 MW Wind | F10: 18 | G10: 650 | H10: 7.8 | I10: 3.8 | J10: 4 | K10: 260 | L10: Captive Hybrid PPA with ReNew & Rooftop | M10: 50% Carbon Reduction by 2035
A11: Bharat Forge Ltd | B11: BHARATFORG | C11: Auto Ancillary & Forging | D11: 52 | E11: 52 MW Solar & Wind installations | F11: 36 | G11: 135 | H11: 8.9 | I11: 3.8 | J11: 5.1 | K11: 68.9 | L11: Group Captive Solar in Maharashtra | M11: Carbon Neutral by 2040
A12: Apollo Tyres Ltd | B12: APOLLOTYRE | C12: Auto Tyres | D12: 48 | E12: 48 MW Solar & Biomass installations | F12: 32 | G12: 120 | H12: 8.6 | I12: 3.75 | J12: 4.85 | K12: 58.2 | L12: Open Access Solar in AP & Gujarat | M12: 25% Carbon Intensity cut by 2026
A13: CEAT Ltd | B13: CEATLTD | C13: Auto Tyres | D13: 38 | E13: 38 MW Solar installations (Halol & Nagpur) | F13: 34 | G13: 95 | H13: 8.7 | I13: 3.8 | J13: 4.9 | K13: 46.6 | L13: Rooftop Solar + Captive Solar PPA | M13: 50% RE by 2030
A14: SRF Ltd | B14: SRF | C14: Specialty Chemicals & Packaging | D14: 65 | E14: 65 MW Solar & Wind power PPAs | F14: 22 | G14: 160 | H14: 8 | I14: 3.85 | J14: 4.15 | K14: 66.4 | L14: Open Access Solar in Rajasthan & MP | M14: 35% RE by 2028
A15: PI Industries Ltd | B15: PIIND | C15: Agrochemicals & Specialty Chem | D15: 28 | E15: 28 MW Solar power plants & rooftop | F15: 31 | G15: 65 | H15: 8.2 | I15: 3.7 | J15: 4.5 | K15: 29.3 | L15: Onsite Rooftop Solar + Offsite Open Access | M15: 45% RE by 2030
A16: Biocon Ltd | B16: BIOCON | C16: Biopharmaceuticals | D16: 22 | E16: 22 MW Solar & Wind PPAs | F16: 48 | G16: 58 | H16: 8.8 | I16: 3.8 | J16: 5 | K16: 29 | L16: Open Access Solar with CleanMax | M16: 70% RE by 2028
... A24: Exide Industries Ltd | B24: EXIDEIND | C24: Batteries & Storage | D24: 35 | E24: 35 MW Solar & Wind installations | F24: 26 | G24: 82 | H24: 8.4 | I24: 3.8 | J24: 4.6 | K24: 37.7 | L24: Rooftop Solar + Haldia captive park | M24: 50% RE by 2030
A25: TOTAL / WEIGHTED AVERAGE | D25: =SUM(D5:D24) | F25: =AVERAGE(F5:F24) | G25: =SUM(G5:G24) | H25: =AVERAGE(H5:H24) | I25: =AVERAGE(I5:I24) | J25: =AVERAGE(J5:J24) | K25: =SUM(K5:K24)

Sheet Small & Micro Cap Companies
A1: India Listed Small & Micro-Cap Companies: Renewable Adoption & Shielded Costs
A2: SEBI 251+ Listed Corporates | High-Growth Small Caps, Textiles, Auto Components & Solar IPPs
A4: Company Name | B4: Ticker | C4: Sector / Industry | D4: Installed / Contracted RE (MW) | E4: Solar / Wind / Green Tech Details | F4: RE Electricity Share (%) | G4: Annual Green Units (MU / MWh M) | H4: Avg. Grid Tariff (₹/kWh) | I4: Green Landed Cost (₹/kWh) | J4: Cost Shielded / Unit Saved (₹/kWh) | K4: Est. Annual Cost Shielded (₹ Crore) | L4: Primary Sourcing Model | M4: Key Targets / Commitments
A5: KPR Mill Ltd | B5: KPRMILL | C5: Textiles & Garments | D5: 191.9 | E5: 61.9 MW Wind + 35 MW Solar + 90 MW Co-gen | F5: 100 | G5: 450 | H5: 8.2 | I5: 3.4 | J5: 4.8 | K5: 216 | L5: Captive Wind & Solar Parks (100% self-reliant) | M5: 100% RE achieved in FY26
A6: Welspun Living Ltd | B6: WELSPUNLIV | C6: Home Textiles | D6: 35 | E6: 35 MW Rooftop & Ground Solar at Anjar & Vapi | F6: 48 | G6: 85 | H6: 8.1 | I6: 3.6 | J6: 4.5 | K6: 38.3 | L6: Rooftop Solar on mega textile parks | M6: 100% RE by 2030 (RE100 member)
A7: Arvind Ltd | B7: ARVIND | C7: Textiles & Apparel | D7: 28 | E7: 28 MW Rooftop Solar at Santej & Naroda | F7: 38 | G7: 62 | H7: 8.2 | I7: 3.65 | J7: 4.55 | K7: 28.2 | L7: Largest rooftop solar installations in textiles | M7: 50% RE by 2028
A8: Sagar Cements Ltd | B8: SAGCEM | C8: Cement | D8: 25.5 | E8: 18 MW Solar + 7.5 MW WHRS | F8: 36 | G8: 78 | H8: 8.1 | I8: 3.7 | J8: 4.4 | K8: 34.3 | L8: Captive Solar Plant at Mattampally & WHRS | M8: 50% Green Power by 2028
A9: Orient Cement Ltd | B9: ORIENTCEM | C9: Cement | D9: 50 | E9: 35 MW Solar PPA + 15 MW WHRS | F9: 38 | G9: 110 | H9: 8 | I9: 3.75 | J9: 4.25 | K9: 46.8 | L9: Solar PPA with Cleantech + WHRS | M9: 55% Green Power by 2030
A10: Birla Corporation Ltd | B10: BIRLACORPN | C10: Cement & Jute | D10: 55 | E10: 35 MW Solar/Wind + 20 MW WHRS | F10: 30 | G10: 135 | H10: 8.1 | I10: 3.75 | J10: 4.35 | K10: 58.7 | L10: Onsite Solar + Open access wind/solar | M10: 45% RE by 2029
A11: Kajaria Ceramics Ltd | B11: KAJARIACER | C11: Tiles & Ceramics | D11: 12.5 | E11: 12.5 MW Rooftop Solar at Gailpur & Malutana | F11: 24 | G11: 28 | H11: 8.5 | I11: 3.7 | J11: 4.8 | K11: 13.4 | L11: Factory Rooftop Solar PV | M11: 35% RE by 2028
A12: Somany Ceramics Ltd | B12: SOMANYCERA | C12: Tiles & Ceramics | D12: 8.5 | E12: 8.5 MW Rooftop Solar across Kadi & Kassar | F12: 20 | G12: 18 | H12: 8.6 | I12: 3.75 | J12: 4.85 | K12: 8.7 | L12: Onsite Rooftop Solar | M12: 30% RE by 2028
A13: Borosil Renewables Ltd | B13: BORORENEW | C13: Solar Glass & Specialty Glass | D13: 10 | E13: 10 MW Captive Solar & Wind installation | F13: 30 | G13: 24 | H13: 8.2 | I13: 3.6 | J13: 4.6 | K13: 11 | L13: Captive Solar PV + Solar Glass production | M13: 50% RE by 2030
A14: Gabriel India Ltd | B14: GABRIEL | C14: Auto Ancillary / Shock Absorbers | D14: 6.5 | E14: 6.5 MW Rooftop Solar across Pune & Hosur | F14: 32 | G14: 14 | H14: 8.9 | I14: 3.8 | J14: 5.1 | K14: 7.1 | L14: Rooftop Solar on factory sheds | M14: 50% RE by 2028
A15: Lumax Auto Tech Ltd | B15: LUMAXTECH | C15: Auto Ancillary / Lighting | D15: 8 | E15: 8 MW Rooftop Solar across 11 plants | F15: 26 | G15: 18 | H15: 8.8 | I15: 3.8 | J15: 5 | K15: 9 | L15: Rooftop Solar installations | M15: 40% RE by 2030
A16: Subros Ltd | B16: SUBROS | C16: Thermal Systems / Auto AC | D16: 5.5 | E16: 5.5 MW Rooftop Solar at Noida & Manesar | F16: 22 | G16: 12 | H16: 8.7 | I16: 3.8 | J16: 4.9 | K16: 5.9 | L16: Rooftop Solar PV | M16: 35% RE by 2029
... A24: Waaree Energies Ltd | B24: WAAREE | C24: Solar PV Modules & Cleantech | D24: 55 | E24: 55 MW Captive Solar + 12 GW Module Mfg | F24: 70 | G24: 110 | H24: 8 | I24: 3.2 | J24: 4.8 | K24: 52.8 | L24: Captive Solar PV for module gigafactories | M24: 100% Green Manufacturing by 2028
A25: TOTAL / WEIGHTED AVERAGE | D25: =SUM(D5:D24) | F25: =AVERAGE(F5:F24) | G25: =SUM(G5:G24) | H25: =AVERAGE(H5:H24) | I25: =AVERAGE(I5:I24) | J25: =AVERAGE(J5:J24) | K25: =SUM(K5:K24)

Sheet Industry Transition & Macro
A1: Macro Industry Landscape: Indian Commercial & Industrial (C&I) Renewable Energy Transition
A2: Total Power Demand, Current Renewable Penetration, Un-transitioned Gap & Regulatory Catalysts
A4: Metric Description | B4: Value | C4: Unit / Context | D4: Source & Benchmark Details
A5: Total Annual Electricity Consumption in India | B5: 1,550 - 1,600 | C5: Billion Units (TWh) | D5: Central Electricity Authority (CEA) FY25-FY26
A6: Commercial & Industrial (C&I) Power Share | B6: 49% - 51% | C6: % of Total Indian Power | D6: Consumes ~750 to 800 Billion kWh annually
A7: Total Installed Solar Open Access Capacity (C&I) | B7: ~32.9 | C7: Gigawatts (GW) | D7: Mercom India Research & Industry Disclosures (2026)
A8: Total Installed C&I Rooftop Solar Capacity | B8: ~11.5 | C8: Gigawatts (GW) | D8: MNRE & Bridge to India (70-80% driven by C&I)
A9: Total Operational C&I Renewable Capacity | B9: ~44.4 | C9: Gigawatts (GW) | D9: Combined Open Access Solar/Wind + Rooftop PV
A10: Current C&I Renewable Electricity Penetration | B10: ~12% - 15% | C10: % of C&I Power Demand | D10: Generates ~90 to 110 Billion Units of clean power
A11: Remaining Un-Transitioned Industry Demand | B11: 85% - 88% | C11: % of C&I Power Demand | D11: Consumes ~650+ Billion Units of coal/grid electricity
A12: Projected C&I Renewable Capacity by FY2028 | B12: 57.0 | C12: Gigawatts (GW) | D12: ICRA & Industry Forecasts (Growing at 26-30% CAGR)
A13: Projected C&I Renewable Capacity by 2030 | B13: 100.0+ | C13: Gigawatts (GW) | D13: Targeting 35-40% green share of Indian C&I electricity
A16: STATE-WISE DISCOM INDUSTRIAL TARIFF vs SOLAR SAVINGS ARBITRAGE
A17: State / Region | B17: DISCOM Industrial Tariff (₹/kWh) | C17: Solar PPA Landed Cost (₹/kWh) | D17: Net Unit Savings (₹/kWh) | E17: Savings Percentage (%) | F17: Key Open Access Policy Highlights
A18: Maharashtra (MSEDCL) | B18: ₹9.20 - ₹11.50 | C18: ₹4.10 - ₹4.50 | D18: ₹5.10 - ₹7.00 | E18: 55% - 62% | F18: High base tariff & cross-subsidy surcharge; strong group captive demand
A19: Gujarat (UGVCL / DGVCL) | B19: ₹7.50 - ₹8.60 | C19: ₹3.50 - ₹3.90 | D19: ₹3.80 - ₹4.80 | E19: 48% - 55% | F19: Green tariff option available; leading solar manufacturing & Kutch RE hub
A20: Tamil Nadu (TANGEDCO) | B20: ₹8.20 - ₹9.40 | C20: ₹3.70 - ₹4.10 | D20: ₹4.40 - ₹5.30 | E20: 52% - 58% | F20: Pioneer in captive wind & solar; massive textile & auto adoption (KPR, Titan)
A21: Karnataka (BESCOM) | B21: ₹7.80 - ₹9.20 | C21: ₹3.50 - ₹3.90 | D21: ₹4.20 - ₹5.40 | E21: 50% - 58% | F21: High solar irradiance (Pavagada); open access hub for IT campuses & data centers
A22: Rajasthan (JVVNL) | B22: ₹8.00 - ₹9.10 | C22: ₹3.20 - ₹3.60 | D22: ₹4.60 - ₹5.50 | E22: 55% - 60% | F22: Lowest solar generation LCOE in India; exporter of green power to other states
A23: Uttar Pradesh (UPPCL) | B23: ₹8.50 - ₹9.80 | C23: ₹3.90 - ₹4.30 | D23: ₹4.50 - ₹5.50 | E23: 50% - 56% | F23: 100 kW open access rules adopted; rapidly rising rooftop solar in Noida/Kanpur
